eventscore/__init__.py
eventscore/core/__init__.py
eventscore/core/abstract.py
eventscore/core/consumers.py
eventscore/core/ecore.py
eventscore/core/exceptions.py
eventscore/core/logging.py
eventscore/core/pipelines.py
eventscore/core/pkg.py
eventscore/core/producers.py
eventscore/core/runners.py
eventscore/core/serializers.py
eventscore/core/streams.py
eventscore/core/types.py
eventscore/core/workers.py
eventscore/decorators.py
eventscore/ext/__init__.py
eventscore/ext/kafka/__init__.py
eventscore/ext/kafka/serializers.py
eventscore/ext/kafka/streams.py
eventscore/ext/redis/__init__.py
eventscore/ext/redis/serializers.py
eventscore/ext/redis/streams.py
eventscore/shortcuts.py
eventscore-0.1.0.dist-info/LICENSE
eventscore-0.1.0.dist-info/METADATA
eventscore-0.1.0.dist-info/WHEEL
eventscore-0.1.0.dist-info/RECORD
