Metadata-Version: 2.3
Name: eventscore
Version: 0.1.0
Summary: Power up your application with event-driven design!
License: MIT
Author: Matvey Ivanov
Author-email: cool.matvey250301@gmail.com
Requires-Python: >=3.11
Classifier: Programming Language :: Python :: 3.11
Classifier: Programming Language :: Python :: 3.12
Classifier: Programming Language :: Python :: 3.13
Classifier: Operating System :: OS Independent
Classifier: License :: OSI Approved :: MIT License
Requires-Dist: kafka-python (==2.1.5)
Requires-Dist: redis (==5.2.1)
Project-URL: Homepage, https://github.com/MatveyIvanov/eventscore
Project-URL: Issues, https://github.com/MatveyIvanov/eventscore/issues
